MANIFEST.in
README.md
setup.cfg
setup.py
openmined.threepio.egg-info/PKG-INFO
openmined.threepio.egg-info/SOURCES.txt
openmined.threepio.egg-info/dependency_links.txt
openmined.threepio.egg-info/not-zip-safe
openmined.threepio.egg-info/top_level.txt
pythreepio/__init__.py
pythreepio/command.py
pythreepio/errors.py
pythreepio/threepio.py
pythreepio/utils.py
static/__init__.py
static/mapped_commands_full.json
tests/__init__.py
tests/test_tf_torch.py
tests/test_tfjs_torch.py
tests/test_torch_tf.py
tests/test_torch_tfjs.py
tests/util.py